[{"String":"G","Fret":0,"Note":"G"},
{"String":"G","Fret":2,"Note":"A"},
{"String":"G","Fret":4,"Note":"B"},
{"String":"G","Fret":5,"Note":"C"},
{"String":"G","Fret":7,"Note":"D"},
{"String":"G","Fret":9,"Note":"E"},
{"String":"G","Fret":10,"Note":"F"},
{"String":"G","Fret":12,"Note":"G"},
{"String":"G","Fret":14,"Note":"A"},
{"String":"G","Fret":16,"Note":"B"},
{"String":"G","Fret":17,"Note":"C"},
{"String":"G","Fret":19,"Note":"D"},
{"String":"G","Fret":21,"Note":"E"},
{"String":"G","Fret":22,"Note":"F"},
{"String":"G","Fret":24,"Note":"G"},
{"String":"G","Fret":26,"Note":"A"},
{"String":"G","Fret":28,"Note":"B"},
{"String":"G","Fret":29,"Note":"C"},
{"String":"G","Fret":1,"Note":"G#"},
{"String":"G","Fret":3,"Note":"A#"},
{"String":"G","Fret":6,"Note":"C#"},
{"String":"G","Fret":8,"Note":"D#"},
{"String":"G","Fret":11,"Note":"F#"},
{"String":"G","Fret":13,"Note":"G#"},
{"String":"G","Fret":15,"Note":"A#"},
{"String":"G","Fret":18,"Note":"C#"},
{"String":"G","Fret":20,"Note":"D#"},
{"String":"G","Fret":23,"Note":"F#"},
{"String":"G","Fret":25,"Note":"G#"},
{"String":"G","Fret":27,"Note":"A#"},
{"String":"G","Fret":1,"Note":"Ab"},
{"String":"G","Fret":3,"Note":"Bb"},
{"String":"G","Fret":6,"Note":"Db"},
{"String":"G","Fret":8,"Note":"Eb"},
{"String":"G","Fret":11,"Note":"Gb"},
{"String":"G","Fret":13,"Note":"Ab"},
{"String":"G","Fret":15,"Note":"Bb"},
{"String":"G","Fret":18,"Note":"Db"},
{"String":"G","Fret":20,"Note":"Eb"},
{"String":"G","Fret":23,"Note":"Gb"},
{"String":"G","Fret":25,"Note":"Ab"},
{"String":"G","Fret":27,"Note":"Bb"},
{"String":"D","Fret":0,"Note":"D"},
{"String":"D","Fret":2,"Note":"E"},
{"String":"D","Fret":3,"Note":"F"},
{"String":"D","Fret":5,"Note":"G"},
{"String":"D","Fret":7,"Note":"A"},
{"String":"D","Fret":9,"Note":"B"},
{"String":"D","Fret":10,"Note":"C"},
{"String":"D","Fret":12,"Note":"D"},
{"String":"D","Fret":14,"Note":"E"},
{"String":"D","Fret":15,"Note":"F"},
{"String":"D","Fret":17,"Note":"G"},
{"String":"D","Fret":19,"Note":"A"},
{"String":"D","Fret":21,"Note":"B"},
{"String":"D","Fret":22,"Note":"C"},
{"String":"D","Fret":24,"Note":"D"},
{"String":"D","Fret":26,"Note":"E"},
{"String":"D","Fret":27,"Note":"F"},
{"String":"D","Fret":29,"Note":"G"},
{"String":"D","Fret":1,"Note":"D#"},
{"String":"D","Fret":4,"Note":"F#"},
{"String":"D","Fret":6,"Note":"G#"},
{"String":"D","Fret":8,"Note":"A#"},
{"String":"D","Fret":11,"Note":"C#"},
{"String":"D","Fret":13,"Note":"D#"},
{"String":"D","Fret":16,"Note":"F#"},
{"String":"D","Fret":18,"Note":"G#"},
{"String":"D","Fret":20,"Note":"A#"},
{"String":"D","Fret":23,"Note":"C#"},
{"String":"D","Fret":25,"Note":"D#"},
{"String":"D","Fret":28,"Note":"F#"},
{"String":"D","Fret":1,"Note":"Eb"},
{"String":"D","Fret":4,"Note":"Gb"},
{"String":"D","Fret":6,"Note":"Ab"},
{"String":"D","Fret":8,"Note":"Bb"},
{"String":"D","Fret":11,"Note":"Db"},
{"String":"D","Fret":13,"Note":"Eb"},
{"String":"D","Fret":16,"Note":"Gb"},
{"String":"D","Fret":18,"Note":"Ab"},
{"String":"D","Fret":20,"Note":"Bb"},
{"String":"D","Fret":23,"Note":"Db"},
{"String":"D","Fret":25,"Note":"Eb"},
{"String":"D","Fret":28,"Note":"Gb"},
{"String":"A","Fret":0,"Note":"A"},
{"String":"A","Fret":2,"Note":"B"},
{"String":"A","Fret":3,"Note":"C"},
{"String":"A","Fret":5,"Note":"D"},
{"String":"A","Fret":7,"Note":"E"},
{"String":"A","Fret":8,"Note":"F"},
{"String":"A","Fret":10,"Note":"G"},
{"String":"A","Fret":12,"Note":"A"},
{"String":"A","Fret":14,"Note":"B"},
{"String":"A","Fret":15,"Note":"C"},
{"String":"A","Fret":17,"Note":"D"},
{"String":"A","Fret":19,"Note":"E"},
{"String":"A","Fret":20,"Note":"F"},
{"String":"A","Fret":22,"Note":"G"},
{"String":"A","Fret":24,"Note":"A"},
{"String":"A","Fret":26,"Note":"B"},
{"String":"A","Fret":27,"Note":"C"},
{"String":"A","Fret":29,"Note":"D"},
{"String":"A","Fret":1,"Note":"A#"},
{"String":"A","Fret":4,"Note":"C#"},
{"String":"A","Fret":6,"Note":"D#"},
{"String":"A","Fret":9,"Note":"F#"},
{"String":"A","Fret":11,"Note":"G#"},
{"String":"A","Fret":13,"Note":"A#"},
{"String":"A","Fret":16,"Note":"C#"},
{"String":"A","Fret":18,"Note":"D#"},
{"String":"A","Fret":21,"Note":"F#"},
{"String":"A","Fret":23,"Note":"G#"},
{"String":"A","Fret":25,"Note":"A#"},
{"String":"A","Fret":28,"Note":"C#"},
{"String":"A","Fret":1,"Note":"Bb"},
{"String":"A","Fret":4,"Note":"Db"},
{"String":"A","Fret":6,"Note":"Eb"},
{"String":"A","Fret":9,"Note":"Gb"},
{"String":"A","Fret":11,"Note":"Ab"},
{"String":"A","Fret":13,"Note":"Bb"},
{"String":"A","Fret":16,"Note":"Db"},
{"String":"A","Fret":18,"Note":"Eb"},
{"String":"A","Fret":21,"Note":"Gb"},
{"String":"A","Fret":23,"Note":"Ab"},
{"String":"A","Fret":25,"Note":"Bb"},
{"String":"A","Fret":28,"Note":"Db"},
{"String":"C","Fret":23,"Note":"B"},
{"String":"C","Fret":24,"Note":"C"},
{"String":"C","Fret":26,"Note":"D"},
{"String":"C","Fret":28,"Note":"E"},
{"String":"C","Fret":29,"Note":"F"},
{"String":"C","Fret":22,"Note":"A#"},
{"String":"C","Fret":25,"Note":"C#"},
{"String":"C","Fret":27,"Note":"D#"},
{"String":"C","Fret":22,"Note":"Bb"},
{"String":"C","Fret":25,"Note":"Db"},
{"String":"C","Fret":27,"Note":"Eb"},
{"String":"C","Fret":0,"Note":"C"},
{"String":"C","Fret":2,"Note":"D"},
{"String":"C","Fret":4,"Note":"E"},
{"String":"C","Fret":5,"Note":"F"},
{"String":"C","Fret":7,"Note":"G"},
{"String":"C","Fret":9,"Note":"A"},
{"String":"C","Fret":11,"Note":"B"},
{"String":"C","Fret":12,"Note":"C"},
{"String":"C","Fret":14,"Note":"D"},
{"String":"C","Fret":16,"Note":"E"},
{"String":"C","Fret":17,"Note":"F"},
{"String":"C","Fret":19,"Note":"G"},
{"String":"C","Fret":21,"Note":"A"},
{"String":"C","Fret":1,"Note":"C#"},
{"String":"C","Fret":3,"Note":"D#"},
{"String":"C","Fret":6,"Note":"F#"},
{"String":"C","Fret":8,"Note":"G#"},
{"String":"C","Fret":10,"Note":"A#"},
{"String":"C","Fret":13,"Note":"C#"},
{"String":"C","Fret":15,"Note":"D#"},
{"String":"C","Fret":18,"Note":"F#"},
{"String":"C","Fret":20,"Note":"G#"},
{"String":"C","Fret":1,"Note":"Db"},
{"String":"C","Fret":3,"Note":"Eb"},
{"String":"C","Fret":6,"Note":"Gb"},
{"String":"C","Fret":8,"Note":"Ab"},
{"String":"C","Fret":10,"Note":"Bb"},
{"String":"C","Fret":13,"Note":"Db"},
{"String":"C","Fret":15,"Note":"Eb"},
{"String":"C","Fret":18,"Note":"Gb"},
{"String":"C","Fret":20,"Note":"Ab"}]